imgbb/__init__.py
imgbb/client.py
pyimgbb-0.3.0a0.dist-info/METADATA
pyimgbb-0.3.0a0.dist-info/WHEEL
pyimgbb-0.3.0a0.dist-info/top_level.txt
pyimgbb-0.3.0a0.dist-info/RECORD
