Metadata-Version: 2.1
Name: pyimgbb
Version: 0.3.0a0
Summary: A simple client for uploading images to imgbb.com
Home-page: https://github.com/mavhungutrezzy/imgbb
Author: Adivhaho Mavhungu
Author-email: adivhahomavhungu@outlook.com
Classifier: Programming Language :: Python :: 3
Classifier: Programming Language :: Python :: 3.6
Classifier: Programming Language :: Python :: 3.7
Classifier: Programming Language :: Python :: 3.8
Classifier: Programming Language :: Python :: 3.9
Classifier: Operating System :: OS Independent
Requires-Dist: requests
Requires-Dist: pillow
Requires-Dist: python-decouple
